superpdf_vl_utils/__init__.py
superpdf_vl_utils/structs.py
superpdf_vl_utils/superpdf_client.py
superpdf_vl_utils/logits_processor/__init__.py
superpdf_vl_utils/logits_processor/vllm_v0_no_repeat_ngram.py
superpdf_vl_utils/logits_processor/vllm_v1_no_repeat_ngram.py
superpdf_vl_utils/post_process/__init__.py
superpdf_vl_utils/post_process/equation_big.py
superpdf_vl_utils/post_process/equation_block.py
superpdf_vl_utils/post_process/equation_double_subscript.py
superpdf_vl_utils/post_process/equation_fix_eqqcolon.py
superpdf_vl_utils/post_process/equation_left_right.py
superpdf_vl_utils/post_process/equation_leq.py
superpdf_vl_utils/post_process/otsl2html.py
superpdf_vl_utils/vlm_client/__init__.py
superpdf_vl_utils/vlm_client/base_client.py
superpdf_vl_utils/vlm_client/http_client.py
superpdf_vl_utils/vlm_client/transformers_client.py
superpdf_vl_utils/vlm_client/utils.py
superpdf_vl_utils/vlm_client/vllm_async_engine_client.py
superpdf_vl_utils/vlm_client/vllm_engine_client.py
superpdf_vl_utils-0.1.13.dist-info/licenses/LICENSE.md
superpdf_vl_utils-0.1.13.dist-info/METADATA
superpdf_vl_utils-0.1.13.dist-info/WHEEL
superpdf_vl_utils-0.1.13.dist-info/top_level.txt
superpdf_vl_utils-0.1.13.dist-info/RECORD
